design.sv
// Code your design here
// 32-Bit ALU Designed by : Keerthivasan S K
module mux4_1(input [1:0] sel,
              input [3:0] in,
              output reg out);
  
  always @ (*)
    case(sel)
      2'b00: out = in[0];
      2'b01: out = in[1];
      2'b10: out = in[2];
      2'b11: out = in[3];
      default: out = 1'bx;
    endcase
  
endmodule

module arith_add(input [31:0] a,
                 input [31:0] b,
                 input sel,
                 output [31:0] out,
                 output Z,
                 output V,
                 output N);
  wire xb;
  xor g0(xb,b[31],sel);
  assign out = sel ? a - b : a + b;
  assign Z = !(out);
  assign V = (a[31] && xb && (!out[31])) || ((!a[31]) && (!xb) && out[31]);
  assign N = out[31];
              
endmodule

module cmp(input [31:0] a,
           input [31:0] b,
           input [1:0] sel,
           output reg [31:0] out);
  wire [31:0] Q;
  wire V, Z, N;
  wire lt, le;
  
  arith_add m0(a, b, 1'b1, Q, Z, V, N);
  xor g1(lt, V, N);
  or g2(le, Z, lt);
  always @(*)
      case(sel)
        2'b01: out = Z;
        2'b10: out = lt;
        2'b11: out = le;
        default: out = 1'bx;
      endcase
  

endmodule

module bitwise_bool(input [31:0] a,
                    input [31:0] b,
                    input [3:0] fn,
                    output [31:0] out);
  genvar i;
  generate
  for(i = 0; i < 32; i = i + 1)
    begin: mux4_1_gen_label
      mux4_1 mux_inst({b[i],a[i]}, fn, out[i]);
    end
  endgenerate
  
endmodule

module shift(input [31:0] a,
             input [31:0] b,
             input [1:0] sel,
             output reg [31:0] out);
  wire [31:0] t0, t1, t3;
  
  assign t0 = a << b;
  assign t1 = a >> b;
  assign t3 = a >>> b;
  always @ (*)
    case(sel)
      2'b00: out = t0;
      2'b01: out = t1;
      2'b11: out = t3;
      default: out = 1'bx;
    endcase
  
endmodule
  
  
  
module ALU(input [31:0] a,
           input [31:0] b,
           input [5:0] fn,
           output reg [31:0] out);
  wire Z, V, N;
  wire [31:0] t0, t1, t2, t3;
  
  genvar i;
  generate
  for(i = 0; i < 32; i = i + 1)
    begin: mux4_1_gen_label
      mux4_1 mux_inst({b[i],a[i]}, fn[3:0], t2[i]);
    end
  endgenerate
  
  cmp m1(a, b, {fn[2],fn[1]}, t0);
  arith_add m2(a, b, fn[0], t1, Z, V, N);
  shift m4(a, b, {fn[1],fn[0]}, t3);
  
  always @ (*)
    case({fn[5],fn[4]})
      2'b00: out = t0;
      2'b01: out = t1;
      2'b10: out = t2;  	
      2'b11: out = t3; 
    endcase
 
endmodule

testbench.sv
// Code your testbench here
// or browse Examples
/*
module t_mux;
  reg [1:0] sel;
  reg in0, in1, in2, in3;
  wire out;
  mux4_1 MUT0(sel,in0, in1, in2, in3, out);
  
  initial
    begin
      $dumpfile("dump.vcd");
      $dumpvars(1,t_mux);
      sel = 0; in0 = 1; in1 = 0; in2 = 1; in3 = 0;
      #5 sel = 1;
      #5 sel = 2;
      #5 sel = 3;
      #5 in0 = 0; in1 = 1; in2 = 0; in3 = 1;
      #5 sel = 1;
      #5 sel = 2;
      #5 sel = 0;
      #5 $finish;
    end
endmodule
*/

/*
module t_arith_add;
  reg [31:0] a,b;
  reg sel;
  wire [31:0] out;
  wire Z, V, N;
  arith_add MUT1(a,b,sel,out,Z,V,N);
  
  initial 
    begin
      $dumpfile("dump.vcd");
      $dumpvars(1,t_arith_add);
      sel = 0; a = 0; b = 0;
      #5 a = 24; b = 57;
      #5 sel = 1;
      #5 b= 24; a = 57;
      #5 a = -1; b = -2; sel = 0;
      #5 a = -3; b = 3;
      //#5 a = 1,07,37,41,821; b = 3;
      #5 b = -3;
      //#5 a = -1,07,37,41,821;
      #5 sel = 1;
      #5 b = 3;
      //#5 a = 1,07,37,41,821;
      #5 $finish;
    end
endmodule
*/
  
/*
module t_cmp;
  reg [31:0] a,b;
  reg [1:0] sel;
  wire [31:0] out;
  cmp MUT2(a, b, sel, out);
  
  initial
    begin
      $dumpfile("dump.vcd");
      $dumpvars(1,t_cmp);
      sel = 0; a = 0; b = 0;
      #5 sel = 1; a= 4; b = 3;
      #5 b = 4;
      #5 b = 5;
      #5 sel = 2;
      #5 b = -1;
      #5 b = 4;
      #5 b = 5;
      #5 sel = 3;
      #5 b = -2;
      #5 b = 4;
      #5 b = 5;
      #5 $finish;
    end

endmodule
*/

/*
module t_bool;
  reg [31:0] a, b;
  reg [3:0] fn;
  wire [31:0] out;
  bitwise_bool MUT3(a, b, fn, out);
  
  initial
    begin
      $dumpfile("dump.vcd");
      $dumpvars(1,t_bool);
      fn = 0; a = 0; b = 0;
      #5 fn = 14; a = 1; b = 2;		// fn = 1110 is OR gate
      #5 a = 3;
      #5 fn = 8;					// fn = 1000 is AND gate
      #5 fn = 6;					// fn = 0110 is XOR gate
      #5 $finish;
    end
  
endmodule
*/

module t_ALU;
  reg [31:0] a, b;
  reg [5:0] fn;
  wire [31:0] out;
  ALU MUT4(a, b, fn, out);
  
  initial
    begin
      $dumpfile("dump.vcd");
      $dumpvars(1,t_ALU);
      $monitor($time, " a = %d, b = %d, fn=%d, out = %d",a,b,fn,out);
      fn = 0; a = 0; b = 0;
      #5 fn = 3; a = 5; b = 9;		// fn = 00_011 is CMPEQ
      #5 fn = 3; a = 9; b = 9;
      #5 fn = 3; a = -2; b = 9;
      #5 fn = 5; a = -2; b = 9;					// fn = 00_101 is CMPLT
      #5 fn = 5; a = -2; a = 9; b = 9;
      #5 fn = 5; a = 11; b = 9;
      #5 fn = 7; a = 11; b = 11; 			// fn = 00_111 is CMPLE
      #5 fn = 7; a = 11; b = 7;
      #5 fn = 7; a = 11; b = 13;
      #5 fn = 16; a = 9; b = 13;					// fn = 01___0 is ADD
      #5 fn = 16; a = -13; b = 13;
      #5 fn = 16; a = -15; b = 13;
      #5 fn = 16; a = -15; b = -15;
      #5 fn = 17;a = -15; b = -15; 					// fn = 01___1 is SUBTRACT
      #5 fn = 17; a = 8; b = -15;
      #5 fn = 17; a = -6; b = 14;
      #5 fn = 6'b101000; a = 3; b = 2;		// fn = 10abcd is Bitwise Boolean
      #5 fn = 6'b100110; a = 3; b = 2;
      #5 fn = 6'b101110; a = 3; b = 2;
      #5 fn = 48; a = 3; b = 1;		// fn = 11__00 is Logcial Left Shift
      #5 fn = 48; a = -1; b = 1;
      #5 fn = 48; a = -1; b = 2;	
      #5 fn = 49; a = -1; b = 2;	// fn = 11__01 is Logical Right Shift
      #5 fn = 49; a = -1; b = 1;
      #5 fn = 51; a = -1; b = 1;	// fn = 11__11 is Arithmetic Right Shift;
      #5 fn = 51; a = -1; b = 2;
      #5 fn = 51; a = -2; b = -1;
      #5 fn = 51; a = 7; b = -1;
      #5 $finish;
    end
  
endmodule

dump.vcd
$date
	Fri Aug  7 18:00:41 2020
$end
$version
	Icarus Verilog
$end
$timescale
	1s
$end
$scope module t_ALU $end
$var wire 32 ! out [31:0] $end
$var reg 32 " a [31:0] $end
$var reg 32 # b [31:0] $end
$var reg 6 $ fn [5:0] $end
$upscope $end
$enddefinitions $end
#0
$dumpvars
b0 $
b0 #
b0 "
b0x !
$end
#5
b0 !
b1001 #
b101 "
b11 $
#10
b1 !
b1001 "
#15
b0 !
b11111111111111111111111111111110 "
#20
b1 !
b101 $
#25
b0 !
b1001 "
#30
b1011 "
#35
b1 !
b1011 #
b111 $
#40
b0 !
b111 #
#45
b1 !
b1101 #
#50
b10110 !
b1001 "
b10000 $
#55
b0 !
b11111111111111111111111111110011 "
#60
b11111111111111111111111111111110 !
b11111111111111111111111111110001 "
#65
b11111111111111111111111111100010 !
b11111111111111111111111111110001 #
#70
b0 !
b10001 $
#75
b10111 !
b1000 "
#80
b11111111111111111111111111101100 !
b1110 #
b11111111111111111111111111111010 "
#85
b10 !
b10 #
b11 "
b101000 $
#90
b1 !
b100110 $
#95
b11 !
b101110 $
#100
b110 !
b1 #
b110000 $
#105
b11111111111111111111111111111110 !
b11111111111111111111111111111111 "
#110
b11111111111111111111111111111100 !
b10 #
#115
b111111111111111111111111111111 !
b110001 $
#120
b1111111111111111111111111111111 !
b1 #
#125
b110011 $
#130
b111111111111111111111111111111 !
b10 #
#135
b0 !
b11111111111111111111111111111111 #
b11111111111111111111111111111110 "
#140
b111 "
